killx/__init__.py
killx/killx.py
killx-0.1.3.dist-info/licenses/LICENSE
killx-0.1.3.dist-info/METADATA
killx-0.1.3.dist-info/WHEEL
killx-0.1.3.dist-info/top_level.txt
killx-0.1.3.dist-info/RECORD
