Metadata-Version: 2.4
Name: killx
Version: 0.1.3
Summary: A lightning-fast, modern Python web framework
Author-email: Pavitroo <pavitraguptadelhi@gmail.com>
License: # Next, LICENSE
Project-URL: Homepage, https://github.com/Pavitroo/killx
Project-URL: Repository, https://github.com/Pavitroo/killx
Keywords: web,framework,http,server,api
Classifier: License :: OSI Approved :: MIT License
Classifier: Programming Language :: Python :: 3
Classifier: Programming Language :: Python :: 3.7
Classifier: Programming Language :: Python :: 3.8
Classifier: Programming Language :: Python :: 3.9
Classifier: Programming Language :: Python :: 3.10
Classifier: Programming Language :: Python :: 3.11
Requires-Python: >=3.7
License-File: LICENSE
Dynamic: license-file
